MANIFEST.in
README
setup.py
quantapp/AQI.AQILabs.Derivatives.dll
quantapp/AQI.AQILabs.Kernel.Adapters.dll
quantapp/AQI.AQILabs.Kernel.dll
quantapp/AQI.AQILabs.SDK.Strategies.dll
quantapp/Accord.Math.Core.dll
quantapp/Accord.Math.dll
quantapp/Accord.dll
quantapp/Common.Logging.Core.dll
quantapp/Common.Logging.dll
quantapp/Newtonsoft.Json.dll
quantapp/QuantApp.Core.dll
quantapp/Quartz.dll
quantapp/__init__.py
quantapp.egg-info/PKG-INFO
quantapp.egg-info/SOURCES.txt
quantapp.egg-info/dependency_links.txt
quantapp.egg-info/top_level.txt