Metadata-Version: 1.2
Name: quantapp
Version: 0.1.8
Summary: QuantApp Libraries for Systematic Investments and Data Science
Home-page: https://www.quantapp.net
Author: Arturo Rodriguez
Author-email: arturo.rodriguez@quantapp.net
License: MIT
Platform: UNKNOWN
Requires-Python: >=3
